README
setup.cfg
setup.py
plugins/__init__.py
plugins/cisco.py
pyang_cisco_plugin.egg-info/PKG-INFO
pyang_cisco_plugin.egg-info/SOURCES.txt
pyang_cisco_plugin.egg-info/dependency_links.txt
pyang_cisco_plugin.egg-info/entry_points.txt
pyang_cisco_plugin.egg-info/requires.txt
pyang_cisco_plugin.egg-info/top_level.txt