Metadata-Version: 1.1
Name: pyang-cisco-plugin
Version: 0.3
Summary: A pyang plugin to validate Cisco native models
Home-page: https://github.com/mjethanandani/pyang-cisco-plugin
Author: Mahesh Jethanandani
Author-email: mjethanandani@gmail.com
License: New-style BSD
Download-URL: https://github.com/mjethanandani/pyang-cisco-plugin/archive/0.1.tar.gz
Keywords: yang,validation
Platform: UNKNOWN
